init_llm/.env.template
init_llm/__init__.py
init_llm/llm_factory.py
init_llm/model_providers.toml
init_llm-0.1.3.dist-info/LICENSE
init_llm-0.1.3.dist-info/METADATA
init_llm-0.1.3.dist-info/WHEEL
init_llm-0.1.3.dist-info/tmprqpm60y8
init_llm-0.1.3.dist-info/top_level.txt
init_llm-0.1.3.dist-info/RECORD
