Metadata-Version: 2.1
Name: init-llm
Version: 0.1.3
Summary: A toolkit for initializing LLMs and embeddings with multiple providers
Home-page: https://github.com/wangrenyuan/init-llm
Author: G
Author-email: G <wangrenyuan@outlook.com>
License: MIT
Project-URL: Homepage, https://github.com/bluemeat0724/init_llm
Project-URL: Documentation, https://github.com/bluemeat0724/init_llm#readme
Project-URL: Repository, https://github.com/bluemeat0724/init_llm.git
Keywords: llm,ai,langchain,openai,embeddings
Classifier: Development Status :: 4 - Beta
Classifier: Intended Audience :: Developers
Classifier: License :: OSI Approved :: MIT License
Classifier: Operating System :: OS Independent
Classifier: Programming Language :: Python :: 3
Classifier: Programming Language :: Python :: 3.10
Classifier: Topic :: Software Development :: Libraries :: Python Modules
Requires-Python: >=3.10
License-File: LICENSE
Requires-Dist: langchain>=0.1.0
Requires-Dist: openai>=1.0.0
Requires-Dist: langchain-openai>=0.0.5
Requires-Dist: langchain-community>=0.0.20
Requires-Dist: toml>=0.10.2
Requires-Dist: python-dotenv>=1.0.0
